{"data":{"agent_did":"6iz6bQL5E6TCQaUeuSmQwX","agent_vk":"47wgZLS9Db1Nyo3TAqb7qGNyVznXNwTkf8gyPtLUHFyZ","endpoint":"https://vas.pps.evernym.com/agency/msg","invite_detail":{"connReqId":"","senderAgencyDetail":{"DID":"","endpoint":"","verKey":""},"senderDetail":{"DID":"","agentKeyDlgProof":{"agentDID":"","agentDelegatedKey":"","signature":""},"logoUrl":"https://robohash.org/62108","name":"JuJuBee779","verKey":"HBKh34wSULcewPskgk4A7NGFMGCnqenvdrM3j8pNebDf"},"statusCode":"","statusMsg":"","targetName":"","threadId":null},"invite_url":null,"public_did":"4mkwctgj6zaDjp8cK5euVF","pw_did":"Fax5xUMxH7sBuvQTDSx8xn","pw_verkey":"8x595Vh5KNT1Us2YFDRnedWqkKW4dNoodorTPfbWhSux","redirect_detail":null,"source_id":"Connection Name","state":4,"their_public_did":null,"their_pw_did":"WgavMdxSke3ziwQnBrRk6g","their_pw_verkey":"HBKh34wSULcewPskgk4A7NGFMGCnqenvdrM3j8pNebDf","uuid":"","version":"2.0"},"state":{"Invitee":{"Completed":{"did_doc":{"@context":"https://w3id.org/did/v1","authentication":[],"id":"WgavMdxSke3ziwQnBrRk6g","publicKey":[{"controller":"WgavMdxSke3ziwQnBrRk6g","id":"WgavMdxSke3ziwQnBrRk6g#keys-1","publicKeyBase58":"HBKh34wSULcewPskgk4A7NGFMGCnqenvdrM3j8pNebDf","type":"Ed25519VerificationKey2018"}],"service":[{"id":"WgavMdxSke3ziwQnBrRk6g;indy","priority":0,"recipientKeys":["HBKh34wSULcewPskgk4A7NGFMGCnqenvdrM3j8pNebDf"],"routingKeys":["ExPFLx4uNjF9jRQJV7XxAt8MfuXJENgbgA1qNmWznsRZ"],"serviceEndpoint":"https://vas.pps.evernym.com/agency/msg","type":"IndyAgent"}]},"invitation":{"ConnectionInvitation":{"@id":"6bb53b8a-9e9a-43e5-b5c5-332639e09a33","label":"JuJuBee779","profileUrl":"https://robohash.org/62108","recipientKeys":["HBKh34wSULcewPskgk4A7NGFMGCnqenvdrM3j8pNebDf"],"routingKeys":["ExPFLx4uNjF9jRQJV7XxAt8MfuXJENgbgA1qNmWznsRZ"],"serviceEndpoint":"https://vas.pps.evernym.com/agency/msg"}},"protocols":null,"thread":{"received_orders":{"WgavMdxSke3ziwQnBrRk6g":0},"sender_order":1,"thid":"d9c5b2a8-e3a8-4fc1-80f3-0de2c4c54cc2"}}}},"version":"2.0"}
